knncolle/build_index.py
knncolle/kmknn.py
knncolle/query_distance.py
knncolle/__init__.py
knncolle/define_builder.py
knncolle/query_neighbors.py
knncolle/hnsw.py
knncolle/exhaustive.py
knncolle/vptree.py
knncolle/find_neighbors.py
knncolle/classes.py
knncolle/query_knn.py
knncolle/find_distance.py
knncolle/lib_knncolle.cpython-311-darwin.so
knncolle/find_knn.py
knncolle/_utils.py
knncolle/annoy.py
knncolle/include/knncolle_py.h
knncolle-0.3.0.dist-info/RECORD
knncolle-0.3.0.dist-info/WHEEL
knncolle-0.3.0.dist-info/top_level.txt
knncolle-0.3.0.dist-info/METADATA
knncolle-0.3.0.dist-info/licenses/LICENSE.txt
