Metadata-Version: 2.4
Name: knncolle
Version: 0.3.0
Summary: Nearest Neighbor Detection for Bioconductor
Home-page: https://github.com/knncolle/knncolle-py
Author: "Aaron Lun"
Author-email: infinite.monkeys.with.keyboards@gmail.com
License: MIT
Project-URL: Documentation, https://github.com/knncolle/knncolle-py
Platform: any
Classifier: Development Status :: 4 - Beta
Classifier: Programming Language :: Python
Requires-Python: >=3.8
License-File: LICENSE.txt
Requires-Dist: importlib-metadata; python_version < "3.8"
Requires-Dist: numpy>=1.22.4
Provides-Extra: testing
Requires-Dist: setuptools; extra == "testing"
Requires-Dist: pytest; extra == "testing"
Requires-Dist: pytest-cov; extra == "testing"
Requires-Dist: scipy; extra == "testing"
Dynamic: license-file
